{
  "timestamp": "2026-03-12T09:26:01.984940",
  "config": {
    "price": {
      "csv_path": "data_testing_with_month_int.csv",
      "columns": {
        "commodity": "commodity",
        "value": "average_price",
        "year": "year",
        "month": "month",
        "week": "week"
      }
    },
    "volume": {
      "csv_path": "app/agricultural_data.csv",
      "columns": {
        "commodity": "Commodity",
        "value": "Volume",
        "date": "Date"
      }
    },
    "commodities": [
      "Cabbage",
      "Tomato",
      "Potato",
      "Carrots",
      "Green_Onion",
      "Lettuce",
      "Eggplant",
      "Cucumber",
      "Cauliflower",
      "Petchay",
      "Pepper",
      "Squash",
      "Sayote",
      "Broccoli",
      "Camote",
      "Ginger",
      "Beans",
      "Radish"
    ],
    "sequence_length": 4,
    "epochs": 100,
    "test_weeks": 8,
    "model_dir": "models",
    "plot_dir": "plots"
  },
  "results": [
    {
      "commodity": "Cabbage",
      "data_type": "price",
      "status": "SUCCESS",
      "accuracy": 69.51282309385539,
      "mae": 27.651085376739502,
      "weeks_trained": 55
    },
    {
      "commodity": "Tomato",
      "data_type": "price",
      "status": "SUCCESS",
      "accuracy": 54.17103900161444,
      "mae": 45.86900568008423,
      "weeks_trained": 55
    },
    {
      "commodity": "Potato",
      "data_type": "price",
      "status": "SUCCESS",
      "accuracy": 72.54346820030338,
      "mae": 23.305716514587402,
      "weeks_trained": 55
    },
    {
      "commodity": "Carrots",
      "data_type": "price",
      "status": "SUCCESS",
      "accuracy": 48.008328911936516,
      "mae": 66.78746366500854,
      "weeks_trained": 55
    },
    {
      "commodity": "Green_Onion",
      "data_type": "price",
      "status": "SUCCESS",
      "accuracy": 89.73802039673278,
      "mae": 6.733602046966553,
      "weeks_trained": 55
    },
    {
      "commodity": "Lettuce",
      "data_type": "price",
      "status": "SUCCESS",
      "accuracy": 78.01638191897852,
      "mae": 50.15155792236328,
      "weeks_trained": 55
    },
    {
      "commodity": "Eggplant",
      "data_type": "price",
      "status": "SUCCESS",
      "accuracy": 70.82252946388498,
      "mae": 14.090139865875244,
      "weeks_trained": 55
    },
    {
      "commodity": "Cucumber",
      "data_type": "price",
      "status": "SUCCESS",
      "accuracy": 64.76439931832246,
      "mae": 21.152165412902832,
      "weeks_trained": 55
    },
    {
      "commodity": "Cauliflower",
      "data_type": "price",
      "status": "SUCCESS",
      "accuracy": 86.86663987901476,
      "mae": 26.88996124267578,
      "weeks_trained": 51
    },
    {
      "commodity": "Squash",
      "data_type": "price",
      "status": "SUCCESS",
      "accuracy": 0.0,
      "mae": 28.59593915939331,
      "weeks_trained": 55
    },
    {
      "commodity": "Sayote",
      "data_type": "price",
      "status": "SUCCESS",
      "accuracy": 0.0,
      "mae": 28.13207197189331,
      "weeks_trained": 55
    },
    {
      "commodity": "Broccoli",
      "data_type": "price",
      "status": "SUCCESS",
      "accuracy": 88.86664737799228,
      "mae": 29.586885452270508,
      "weeks_trained": 53
    },
    {
      "commodity": "Camote",
      "data_type": "price",
      "status": "SUCCESS",
      "accuracy": 93.4476166247083,
      "mae": 80.88482666015625,
      "weeks_trained": 55
    },
    {
      "commodity": "Ginger",
      "data_type": "price",
      "status": "SUCCESS",
      "accuracy": 63.55782318115234,
      "mae": 27.331632614135742,
      "weeks_trained": 55
    },
    {
      "commodity": "Radish",
      "data_type": "price",
      "status": "SUCCESS",
      "accuracy": 56.91315986323014,
      "mae": 44.040260314941406,
      "weeks_trained": 55
    },
    {
      "commodity": "Cabbage",
      "data_type": "volume",
      "status": "SUCCESS",
      "accuracy": 98.95621127918578,
      "mae": 73.39765624999973,
      "weeks_trained": 8
    },
    {
      "commodity": "Tomato",
      "data_type": "volume",
      "status": "SUCCESS",
      "accuracy": 93.5802884048974,
      "mae": 347.6666015625001,
      "weeks_trained": 8
    },
    {
      "commodity": "Potato",
      "data_type": "volume",
      "status": "SUCCESS",
      "accuracy": 98.03202961386765,
      "mae": 169.36054687500018,
      "weeks_trained": 8
    }
  ]
}